LICENCE
README.md
setup.py
gerenciamento_software/__init__.py
gerenciamento_software/comandos_gerais.py
gerenciamento_software/criptografia.py
gerenciamento_software/infos.py
gerenciamento_software/logs.py
gerenciamento_software/sql.py
gerenciamento_software/uteis.py
gerenciamento_software/validacao.py
gerenciamento_software.egg-info/PKG-INFO
gerenciamento_software.egg-info/SOURCES.txt
gerenciamento_software.egg-info/dependency_links.txt
gerenciamento_software.egg-info/requires.txt
gerenciamento_software.egg-info/top_level.txt