Metadata-Version: 2.1
Name: gerenciamento-software
Version: 2.0.2
Summary: Conjunto De Ferramentas Para Gerenciar Um Software
Author: George Júnior
Author-email: ctt.georgejr@gmail.com
License: MIT License
Keywords: gerenciamento de software
License-File: LICENCE
